{"birth_date": "1986-04-10", "gender": "F", "events": [{"date": "2013-04-03", "code": "V70.0", "system": "http://hl7.org/fhir/sid/icd-9-cm"}, {"date": "2013-02-25", "code": "757.32", "system": "http://hl7.org/fhir/sid/icd-9-cm"}, {"date": "2013-02-16", "code": "V30.00", "system": "http://hl7.org/fhir/sid/icd-9-cm"}, {"date": "2013-02-14", "code": "779.84", "system": "http://hl7.org/fhir/sid/icd-9-cm"}, {"date": "2013-02-14", "code": "650", "system": "http://hl7.org/fhir/sid/icd-9-cm"}, {"date": "2013-02-13", "code": "650", "system": "http://hl7.org/fhir/sid/icd-9-cm"}, {"date": "2013-02-13", "code": "664.11", "system": "http://hl7.org/fhir/sid/icd-9-cm"}, {"date": "2013-01-21", "code": "644.13", "system": "http://hl7.org/fhir/sid/icd-9-cm"}, {"date": "2013-01-11", "code": "V04.81", "system": "http://hl7.org/fhir/sid/icd-9-cm"}, {"date": "2013-01-11", "code": "V22.2", "system": "http://hl7.org/fhir/sid/icd-9-cm"}]}